pylive_played_clip/__init__.py
pylive_played_clip/__main__.py
pylive_played_clip/py.typed
pylive_played_clip-1.1.7.dist-info/LICENSE
pylive_played_clip-1.1.7.dist-info/METADATA
pylive_played_clip-1.1.7.dist-info/WHEEL
pylive_played_clip-1.1.7.dist-info/entry_points.txt
pylive_played_clip-1.1.7.dist-info/top_level.txt
pylive_played_clip-1.1.7.dist-info/RECORD
