Metadata-Version: 2.1
Name: pylive-played-clip
Version: 1.1.7
Summary: A tool to monitor Ableton Live and update the color of clips that have been played.
Home-page: https://github.com/saselberg/pylive-played-clip
Author: Scott Selberg
Author-email: saselberg@gmail.com
Project-URL: Source, https://github.com/saselberg/pylive-played-clip
Project-URL: Documentation, https://pylive-played-clip.readthedocs.io/en/latest/
Project-URL: PyPI Package, https://pypi.org/project/pylive-played-clip/
Classifier: License :: OSI Approved :: BSD License
Classifier: Programming Language :: Python :: 3
Classifier: Operating System :: OS Independent
Requires-Python: >=3.8
License-File: LICENSE
Requires-Dist: pylive
Provides-Extra: dev
Requires-Dist: build ; extra == 'dev'
Requires-Dist: flake8 ; extra == 'dev'
Requires-Dist: linuxdoc ; extra == 'dev'
Requires-Dist: markupsafe ; extra == 'dev'
Requires-Dist: mypy ; extra == 'dev'
Requires-Dist: myst-parser ; extra == 'dev'
Requires-Dist: pyright ; extra == 'dev'
Requires-Dist: pytest ; extra == 'dev'
Requires-Dist: sphinx ; extra == 'dev'
Requires-Dist: sphinx-rtd-theme ; extra == 'dev'
Requires-Dist: sphinx-argparse ; extra == 'dev'
Requires-Dist: sphinx-copybutton ; extra == 'dev'
Requires-Dist: sphinx-toolbox ; extra == 'dev'
Requires-Dist: twine ; extra == 'dev'
Requires-Dist: types-pytest-lazy-fixture ; extra == 'dev'
Requires-Dist: types-setuptools ; extra == 'dev'
